LICENSE
MANIFEST.in
README.rst
requirements-dependency_graphs.txt
requirements-gantt.txt
setup.py
ActionTree/__init__.py
ActionTree/stock.py
ActionTree.egg-info/PKG-INFO
ActionTree.egg-info/SOURCES.txt
ActionTree.egg-info/dependency_links.txt
ActionTree.egg-info/requires.txt
ActionTree.egg-info/top_level.txt
ActionTree/tests/__init__.py
ActionTree/tests/capture_output.py
ActionTree/tests/dependency_cycle.py
ActionTree/tests/dependency_graph.py
ActionTree/tests/exceptions_handling.py
ActionTree/tests/gantt_chart.py
ActionTree/tests/hooks.py
ActionTree/tests/multi_threaded_execution.py
ActionTree/tests/multiple_executions.py
ActionTree/tests/picklability.py
ActionTree/tests/possible_execution_order.py
ActionTree/tests/process_wide_state.py
ActionTree/tests/single_threaded_execution.py
ActionTree/tests/stock_actions.py
ActionTree/tests/timing.py